Workbook
Name CHActCashBalance: #REF!
Name CHExpenseForcast: #REF!
Name CHFundrasingForcast: #REF!
Name CHManagementForcast: #REF!
Name CHQ4CashAvailableMonth: #REF!
Name CHQ4CashBalance: #REF!
Name CHRevenueForcast: #REF!
Name CHYTDExpense: #REF!
Name CHYTDRevenue: #REF!
Name CHYTDRevenueVariance: #REF!
Name Combined: #REF!
Name CombinedForcastNet: #REF!
Name CombinedYTDExpense: #REF!
Name CombinedYTDExpenseVariance: #REF!
Name CombinedYTDNet: #REF!
Name CombinedYTDNetVariance: #REF!
Name CombinedYTDRevenue: #REF!
Name CombinedYTDVariance: #REF!
Name ConbimedExpenseForcast: #REF!
Name ConbimedProgramExpenseForcast: #REF!
Name NewCountryForcast: #REF!
Name NewCountryForcastVariance: #REF!
Name NewCountryYTD: #REF!
Name NewcountryYTDVariance: #REF!
Name OSCashalance: #REF!
Name OSCashalanceAct: #REF!
Name OSCashEndBalance: #REF!
Name OSExpenseForcast: #REF!
Name OSExpenseForcastRenovation: #REF!
Name OSForcastNet: #REF!
Name OSForcastNetVariance: #REF!
Name OSFundrasingForcast: #REF!
Name OSHKCenterCashBalance: #REF!
Name OSManagementForcast: #REF!
Name OSProgramAnnual: #REF!
Name OSRevenueForcast: #REF!
Name OSRevenueForcastVariance: #REF!
Name OSYTDExpense: #REF!
Name OSYTDExpenseVariance: #REF!
Name OSYTDNet: #REF!
Name OSYTDRevenue: #REF!
Name OSYTDRevenueVariance: #REF!
Name RateOSAnnualVsLast: #REF!
Name RateOSYTDRevenue: #REF!
Name UnresNetAnnual: #REF!
Name UnresNetDiff: #REF!
Name UnresNetYTD: #REF!
Name YTDCashBalance: #REF!
Name YTDMonthOfCash: #REF!

Sheet salary allocation-v2
D2: OneSky Vietnam
D3: Salary Allocation Projection - PACCOM report Period: Sep 2025 - Dec 2025 | E3: VNELC | F3: VNDN | G3: VNQN | H3: VNHD | I3: VNQNg | J3: VNMOET | O3: ='[1]C&G Ledger_allocation'!AP9 -> ELC Operation | P3: ='[1]C&G Ledger_allocation'!AQ9 -> ELC training | Q3: ='[1]C&G Ledger_allocation'!AR9 -> In support | R3: ='[1]C&G Ledger_allocation'!AS9 -> General VN | S3: ='[1]C&G Ledger_allocation'!AT9 -> DN ICC | T3: ='[1]C&G Ledger_allocation'!AU9 -> QN ICC | U3: ='[1]C&G Ledger_allocation'!AV9 -> HD ICC | V3: ='[1]C&G Ledger_allocation'!AW9 -> QNg ICC | ... AB3: ='[1]C&G Ledger_allocation'!BC9 -> MOET BG
E4: 1 | F4: 2 | G4: 3 | H4: 4 | I4: 5 | J4: 6 | K4: 6 Unit | O4: Current booking | AD4: Allocation
A5: STT | C5: Group | D5: Salary Allocation 2024 | E5: ELC | F5: ICC DN | G5: ICC QN | H5: ICC HD | I5: ICC Qng | J5: Dự án tập huấn toàn quốc/ National Training | K5: Total | L5: Note | M5: Portion | N5: Month | O5: ELC Operation | P5: ELC training | Q5: In support | R5: General VN | S5: DN ICC | T5: QN ICC | U5: HD ICC | V5: QNg ICC | W5: MOET | X5: MOET LA | Y5: MOET HCM | Z5: MOET BD | AA5: MOET BN | AB5: MOET BG | AC5: Total | AD5: ELC training | AE5: ICC DN | AF5: ICC QN | AG5: ICC HD | AH5: ICC Qng | AI5: Dự án tập huấn toàn quốc/ National Training | AJ5: Total
A6: 1 | B6: Hien Thi Hien Vo | C6: Support | D6: Hien Thi Hien Vo | E6: 0 | F6: ='[1]salary allocation'!F6 -> 0.1 | G6: ='[1]salary allocation'!G6 -> 0.1 | H6: ='[1]salary allocation'!H6 -> 0.1 | J6: ='[1]salary allocation'!E6+'[1]salary allocation'!J6 -> 0.7 | K6: =SUM(E6:J6) -> 1 | M6: 5 | N6: 12024 | O6: =SUMIFS('[1]C&G Ledger_allocation'!AP:AP,'[1]C&G Ledger_allocation'!$H:$H,'salary allocation-v2'!$D6,'[1]C&G Ledger_allocation'!$A:$A,'salary allocation-v2'!$N6) -> #VALUE! | P6: =SUMIFS('[1]C&G Ledger_allocation'!AQ:AQ,'[1]C&G Ledger_allocation'!$H:$H,'salary allocation-v2'!$D6,'[1]C&G Ledger_allocation'!$A:$A,'salary allocation-v2'!$N6) -> #VALUE! | Q6: =SUMIFS('[1]C&G Ledger_allocation'!AR:AR,'[1]C&G Ledger_allocation'!$H:$H,'salary allocation-v2'!$D6,'[1]C&G Ledger_allocation'!$A:$A,'salary allocation-v2'!$N6) -> #VALUE! | R6: =SUMIFS('[1]C&G Ledger_allocation'!AS:AS,'[1]C&G Ledger_allocation'!$H:$H,'salary allocation-v2'!$D6,'[1]C&G Ledger_allocation'!$A:$A,'salary allocation-v2'!$N6) -> #VALUE! | S6: =SUMIFS('[1]C&G Ledger_allocation'!AT:AT,'[1]C&G Ledger_allocation'!$H:$H,'salary allocation-v2'!$D6,'[1]C&G Ledger_allocation'!$A:$A,'salary allocation-v2'!$N6) -> #VALUE! | T6: =SUMIFS('[1]C&G Ledger_allocation'!AU:AU,'[1]C&G Ledger_allocation'!$H:$H,'salary allocation-v2'!$D6,'[1]C&G Ledger_allocation'!$A:$A,'salary allocation-v2'!$N6) -> #VALUE! | U6: =SUMIFS('[1]C&G Ledger_allocation'!AV:AV,'[1]C&G Ledger_allocation'!$H:$H,'salary allocation-v2'!$D6,'[1]C&G Ledger_allocation'!$A:$A,'salary allocation-v2'!$N6) -> #VALUE! | V6: =SUMIFS('[1]C&G Ledger_allocation'!AW:AW,'[1]C&G Ledger_allocation'!$H:$H,'salary allocation-v2'!$D6,'[1]C&G Ledger_allocation'!$A:$A,'salary allocation-v2'!$N6) -> #VALUE! | W6: =SUMIFS('[1]C&G Ledger_allocation'!AX:AX,'[1]C&G Ledger_allocation'!$H:$H,'salary allocation-v2'!$D6,'[1]C&G Ledger_allocation'!$A:$A,'salary allocation-v2'!$N6) -> #VALUE! | X6: =SUMIFS('[1]C&G Ledger_allocation'!AY:AY,'[1]C&G Ledger_allocation'!$H:$H,'salary allocation-v2'!$D6,'[1]C&G Ledger_allocation'!$A:$A,'salary allocation-v2'!$N6) -> #VALUE! | Y6: =SUMIFS('[1]C&G Ledger_allocation'!AZ:AZ,'[1]C&G Ledger_allocation'!$H:$H,'salary allocation-v2'!$D6,'[1]C&G Ledger_allocation'!$A:$A,'salary allocation-v2'!$N6) -> #VALUE! | Z6: =SUMIFS('[1]C&G Ledger_allocation'!BA:BA,'[1]C&G Ledger_allocation'!$H:$H,'salary allocation-v2'!$D6,'[1]C&G Ledger_allocation'!$A:$A,'salary allocation-v2'!$N6) -> #VALUE! | AA6: =SUMIFS('[1]C&G Ledger_allocation'!BB:BB,'[1]C&G Ledger_allocation'!$H:$H,'salary allocation-v2'!$D6,'[1]C&G Ledger_allocation'!$A:$A,'salary allocation-v2'!$N6) -> #VALUE! | AB6: =SUMIFS('[1]C&G Ledger_allocation'!BC:BC,'[1]C&G Ledger_allocation'!$H:$H,'salary allocation-v2'!$D6,'[1]C&G Ledger_allocation'!$A:$A,'salary allocation-v2'!$N6) -> #VALUE! | AC6: =Q6 -> #VALUE! | AD6: =$AC6*E6 -> #VALUE! | AE6: =$AC6*F6 -> #VALUE! | AF6: =$AC6*G6 -> #VALUE! | AG6: =$AC6*H6 -> #VALUE! | AH6: =$AC6*I6 -> #VALUE! | AI6: =$AC6*J6 -> #VALUE! | AJ6: =SUM(AD6:AI6) -> #VALUE! | AK6: =AC6-AJ6 -> #VALUE!
A7: =A6+1 -> 2 | B7: Thuy Thi Bich Thuy Tran | C7: Support | D7: Sophie Nguyen Thi Bao Nhung | E7: 0 | F7: ='[1]salary allocation'!F7 -> 0.2 | G7: ='[1]salary allocation'!G7 -> 0.2 | H7: ='[1]salary allocation'!H7 -> 0.2 | J7: ='[1]salary allocation'!E7+'[1]salary allocation'!J7 -> 0.4 | K7: =SUM(E7:J7) -> 1 | M7: 5 | N7: 12024 | O7: =SUMIFS('[1]C&G Ledger_allocation'!AP:AP,'[1]C&G Ledger_allocation'!$H:$H,'salary allocation-v2'!$D7,'[1]C&G Ledger_allocation'!$A:$A,'salary allocation-v2'!$N7) -> #VALUE! | P7: =SUMIFS('[1]C&G Ledger_allocation'!AQ:AQ,'[1]C&G Ledger_allocation'!$H:$H,'salary allocation-v2'!$D7,'[1]C&G Ledger_allocation'!$A:$A,'salary allocation-v2'!$N7) -> #VALUE! | Q7: =SUMIFS('[1]C&G Ledger_allocation'!AR:AR,'[1]C&G Ledger_allocation'!$H:$H,'salary allocation-v2'!$D7,'[1]C&G Ledger_allocation'!$A:$A,'salary allocation-v2'!$N7) -> #VALUE! | R7: =SUMIFS('[1]C&G Ledger_allocation'!AS:AS,'[1]C&G Ledger_allocation'!$H:$H,'salary allocation-v2'!$D7,'[1]C&G Ledger_allocation'!$A:$A,'salary allocation-v2'!$N7) -> #VALUE! | S7: =SUMIFS('[1]C&G Ledger_allocation'!AT:AT,'[1]C&G Ledger_allocation'!$H:$H,'salary allocation-v2'!$D7,'[1]C&G Ledger_allocation'!$A:$A,'salary allocation-v2'!$N7) -> #VALUE! | T7: =SUMIFS('[1]C&G Ledger_allocation'!AU:AU,'[1]C&G Ledger_allocation'!$H:$H,'salary allocation-v2'!$D7,'[1]C&G Ledger_allocation'!$A:$A,'salary allocation-v2'!$N7) -> #VALUE! | U7: =SUMIFS('[1]C&G Ledger_allocation'!AV:AV,'[1]C&G Ledger_allocation'!$H:$H,'salary allocation-v2'!$D7,'[1]C&G Ledger_allocation'!$A:$A,'salary allocation-v2'!$N7) -> #VALUE! | V7: =SUMIFS('[1]C&G Ledger_allocation'!AW:AW,'[1]C&G Ledger_allocation'!$H:$H,'salary allocation-v2'!$D7,'[1]C&G Ledger_allocation'!$A:$A,'salary allocation-v2'!$N7) -> #VALUE! | W7: =SUMIFS('[1]C&G Ledger_allocation'!AX:AX,'[1]C&G Ledger_allocation'!$H:$H,'salary allocation-v2'!$D7,'[1]C&G Ledger_allocation'!$A:$A,'salary allocation-v2'!$N7) -> #VALUE! | X7: =SUMIFS('[1]C&G Ledger_allocation'!AY:AY,'[1]C&G Ledger_allocation'!$H:$H,'salary allocation-v2'!$D7,'[1]C&G Ledger_allocation'!$A:$A,'salary allocation-v2'!$N7) -> #VALUE! | Y7: =SUMIFS('[1]C&G Ledger_allocation'!AZ:AZ,'[1]C&G Ledger_allocation'!$H:$H,'salary allocation-v2'!$D7,'[1]C&G Ledger_allocation'!$A:$A,'salary allocation-v2'!$N7) -> #VALUE! | Z7: =SUMIFS('[1]C&G Ledger_allocation'!BA:BA,'[1]C&G Ledger_allocation'!$H:$H,'salary allocation-v2'!$D7,'[1]C&G Ledger_allocation'!$A:$A,'salary allocation-v2'!$N7) -> #VALUE! | AA7: =SUMIFS('[1]C&G Ledger_allocation'!BB:BB,'[1]C&G Ledger_allocation'!$H:$H,'salary allocation-v2'!$D7,'[1]C&G Ledger_allocation'!$A:$A,'salary allocation-v2'!$N7) -> #VALUE! | AB7: =SUMIFS('[1]C&G Ledger_allocation'!BC:BC,'[1]C&G Ledger_allocation'!$H:$H,'salary allocation-v2'!$D7,'[1]C&G Ledger_allocation'!$A:$A,'salary allocation-v2'!$N7) -> #VALUE! | AC7: =Q7 -> #VALUE! | AD7: =$AC7*E7 -> #VALUE! | AE7: =$AC7*F7 -> #VALUE! | AF7: =$AC7*G7 -> #VALUE! | AG7: =$AC7*H7 -> #VALUE! | AH7: =$AC7*I7 -> #VALUE! | AI7: =$AC7*J7 -> #VALUE! | AJ7: =SUM(AD7:AI7) -> #VALUE! | AK7: =AC7-AJ7 -> #VALUE!
A8: =A7+1 -> 3 | B8: Que Chi | C8: MOET | D8: Truong Thi Hai | E8: 0 | F8: ='[1]salary allocation'!F8 -> 0.2 | G8: ='[1]salary allocation'!G8 -> 0.2 | H8: ='[1]salary allocation'!H8 -> 0.2 | J8: ='[1]salary allocation'!E8+'[1]salary allocation'!J8 -> 0.4 | K8: =SUM(E8:J8) -> 1 | M8: 5 | N8: 12024 | O8: =SUMIFS('[1]C&G Ledger_allocation'!AP:AP,'[1]C&G Ledger_allocation'!$H:$H,'salary allocation-v2'!$D8,'[1]C&G Ledger_allocation'!$A:$A,'salary allocation-v2'!$N8) -> #VALUE! | P8: =SUMIFS('[1]C&G Ledger_allocation'!AQ:AQ,'[1]C&G Ledger_allocation'!$H:$H,'salary allocation-v2'!$D8,'[1]C&G Ledger_allocation'!$A:$A,'salary allocation-v2'!$N8) -> #VALUE! | Q8: =SUMIFS('[1]C&G Ledger_allocation'!AR:AR,'[1]C&G Ledger_allocation'!$H:$H,'salary allocation-v2'!$D8,'[1]C&G Ledger_allocation'!$A:$A,'salary allocation-v2'!$N8) -> #VALUE! | R8: =SUMIFS('[1]C&G Ledger_allocation'!AS:AS,'[1]C&G Ledger_allocation'!$H:$H,'salary allocation-v2'!$D8,'[1]C&G Ledger_allocation'!$A:$A,'salary allocation-v2'!$N8) -> #VALUE! | S8: =SUMIFS('[1]C&G Ledger_allocation'!AT:AT,'[1]C&G Ledger_allocation'!$H:$H,'salary allocation-v2'!$D8,'[1]C&G Ledger_allocation'!$A:$A,'salary allocation-v2'!$N8) -> #VALUE! | T8: =SUMIFS('[1]C&G Ledger_allocation'!AU:AU,'[1]C&G Ledger_allocation'!$H:$H,'salary allocation-v2'!$D8,'[1]C&G Ledger_allocation'!$A:$A,'salary allocation-v2'!$N8) -> #VALUE! | U8: =SUMIFS('[1]C&G Ledger_allocation'!AV:AV,'[1]C&G Ledger_allocation'!$H:$H,'salary allocation-v2'!$D8,'[1]C&G Ledger_allocation'!$A:$A,'salary allocation-v2'!$N8) -> #VALUE! | V8: =SUMIFS('[1]C&G Ledger_allocation'!AW:AW,'[1]C&G Ledger_allocation'!$H:$H,'salary allocation-v2'!$D8,'[1]C&G Ledger_allocation'!$A:$A,'salary allocation-v2'!$N8) -> #VALUE! | W8: =SUMIFS('[1]C&G Ledger_allocation'!AX:AX,'[1]C&G Ledger_allocation'!$H:$H,'salary allocation-v2'!$D8,'[1]C&G Ledger_allocation'!$A:$A,'salary allocation-v2'!$N8) -> #VALUE! | X8: =SUMIFS('[1]C&G Ledger_allocation'!AY:AY,'[1]C&G Ledger_allocation'!$H:$H,'salary allocation-v2'!$D8,'[1]C&G Ledger_allocation'!$A:$A,'salary allocation-v2'!$N8) -> #VALUE! | Y8: =SUMIFS('[1]C&G Ledger_allocation'!AZ:AZ,'[1]C&G Ledger_allocation'!$H:$H,'salary allocation-v2'!$D8,'[1]C&G Ledger_allocation'!$A:$A,'salary allocation-v2'!$N8) -> #VALUE! | Z8: =SUMIFS('[1]C&G Ledger_allocation'!BA:BA,'[1]C&G Ledger_allocation'!$H:$H,'salary allocation-v2'!$D8,'[1]C&G Ledger_allocation'!$A:$A,'salary allocation-v2'!$N8) -> #VALUE! | AA8: =SUMIFS('[1]C&G Ledger_allocation'!BB:BB,'[1]C&G Ledger_allocation'!$H:$H,'salary allocation-v2'!$D8,'[1]C&G Ledger_allocation'!$A:$A,'salary allocation-v2'!$N8) -> #VALUE! | AB8: =SUMIFS('[1]C&G Ledger_allocation'!BC:BC,'[1]C&G Ledger_allocation'!$H:$H,'salary allocation-v2'!$D8,'[1]C&G Ledger_allocation'!$A:$A,'salary allocation-v2'!$N8) -> #VALUE! | AC8: =W8 -> #VALUE! | AD8: =$AC8*E8 -> #VALUE! | AE8: =$AC8*F8 -> #VALUE! | AF8: =$AC8*G8 -> #VALUE! | AG8: =$AC8*H8 -> #VALUE! | AH8: =$AC8*I8 -> #VALUE! | AI8: =$AC8*J8 -> #VALUE! | AJ8: =SUM(AD8:AI8) -> #VALUE! | AK8: =AC8-AJ8 -> #VALUE!
A9: =A8+1 -> 4 | B9: Maggie Huyen Nguyen | C9: MOET | D9: Huynh My Ngoc | E9: 0 | F9: ='[1]salary allocation'!F9 -> 0 | G9: ='[1]salary allocation'!G9 -> 0 | H9: ='[1]salary allocation'!H9 -> 0 | J9: ='[1]salary allocation'!E9+'[1]salary allocation'!J9 -> 1 | K9: =SUM(E9:J9) -> 1 | M9: 100% MOET | N9: 12024 | O9: =SUMIFS('[1]C&G Ledger_allocation'!AP:AP,'[1]C&G Ledger_allocation'!$H:$H,'salary allocation-v2'!$D9,'[1]C&G Ledger_allocation'!$A:$A,'salary allocation-v2'!$N9) -> #VALUE! | P9: =SUMIFS('[1]C&G Ledger_allocation'!AQ:AQ,'[1]C&G Ledger_allocation'!$H:$H,'salary allocation-v2'!$D9,'[1]C&G Ledger_allocation'!$A:$A,'salary allocation-v2'!$N9) -> #VALUE! | Q9: =SUMIFS('[1]C&G Ledger_allocation'!AR:AR,'[1]C&G Ledger_allocation'!$H:$H,'salary allocation-v2'!$D9,'[1]C&G Ledger_allocation'!$A:$A,'salary allocation-v2'!$N9) -> #VALUE! | R9: =SUMIFS('[1]C&G Ledger_allocation'!AS:AS,'[1]C&G Ledger_allocation'!$H:$H,'salary allocation-v2'!$D9,'[1]C&G Ledger_allocation'!$A:$A,'salary allocation-v2'!$N9) -> #VALUE! | S9: =SUMIFS('[1]C&G Ledger_allocation'!AT:AT,'[1]C&G Ledger_allocation'!$H:$H,'salary allocation-v2'!$D9,'[1]C&G Ledger_allocation'!$A:$A,'salary allocation-v2'!$N9) -> #VALUE! | T9: =SUMIFS('[1]C&G Ledger_allocation'!AU:AU,'[1]C&G Ledger_allocation'!$H:$H,'salary allocation-v2'!$D9,'[1]C&G Ledger_allocation'!$A:$A,'salary allocation-v2'!$N9) -> #VALUE! | U9: =SUMIFS('[1]C&G Ledger_allocation'!AV:AV,'[1]C&G Ledger_allocation'!$H:$H,'salary allocation-v2'!$D9,'[1]C&G Ledger_allocation'!$A:$A,'salary allocation-v2'!$N9) -> #VALUE! | V9: =SUMIFS('[1]C&G Ledger_allocation'!AW:AW,'[1]C&G Ledger_allocation'!$H:$H,'salary allocation-v2'!$D9,'[1]C&G Ledger_allocation'!$A:$A,'salary allocation-v2'!$N9) -> #VALUE! | W9: =SUMIFS('[1]C&G Ledger_allocation'!AX:AX,'[1]C&G Ledger_allocation'!$H:$H,'salary allocation-v2'!$D9,'[1]C&G Ledger_allocation'!$A:$A,'salary allocation-v2'!$N9) -> #VALUE! | X9: =SUMIFS('[1]C&G Ledger_allocation'!AY:AY,'[1]C&G Ledger_allocation'!$H:$H,'salary allocation-v2'!$D9,'[1]C&G Ledger_allocation'!$A:$A,'salary allocation-v2'!$N9) -> #VALUE! | Y9: =SUMIFS('[1]C&G Ledger_allocation'!AZ:AZ,'[1]C&G Ledger_allocation'!$H:$H,'salary allocation-v2'!$D9,'[1]C&G Ledger_allocation'!$A:$A,'salary allocation-v2'!$N9) -> #VALUE! | Z9: =SUMIFS('[1]C&G Ledger_allocation'!BA:BA,'[1]C&G Ledger_allocation'!$H:$H,'salary allocation-v2'!$D9,'[1]C&G Ledger_allocation'!$A:$A,'salary allocation-v2'!$N9) -> #VALUE! | AA9: =SUMIFS('[1]C&G Ledger_allocation'!BB:BB,'[1]C&G Ledger_allocation'!$H:$H,'salary allocation-v2'!$D9,'[1]C&G Ledger_allocation'!$A:$A,'salary allocation-v2'!$N9) -> #VALUE! | AB9: =SUMIFS('[1]C&G Ledger_allocation'!BC:BC,'[1]C&G Ledger_allocation'!$H:$H,'salary allocation-v2'!$D9,'[1]C&G Ledger_allocation'!$A:$A,'salary allocation-v2'!$N9) -> #VALUE! | AC9: =W9 -> #VALUE! | AD9: =$AC9*E9 -> #VALUE! | AE9: =$AC9*F9 -> #VALUE! | AF9: =$AC9*G9 -> #VALUE! | AG9: =$AC9*H9 -> #VALUE! | AH9: =$AC9*I9 -> #VALUE! | AI9: =$AC9*J9 -> #VALUE! | AJ9: =SUM(AD9:AI9) -> #VALUE! | AK9: =AC9-AJ9 -> #VALUE!
A10: =A9+1 -> 5 | B10: Sophie Nguyen Thi Bao Nhung | C10: MOET | D10: Bui Thi Huong | E10: 0 | F10: ='[1]salary allocation'!F10 -> 0 | G10: ='[1]salary allocation'!G10 -> 0 | H10: ='[1]salary allocation'!H10 -> 0 | J10: ='[1]salary allocation'!E10+'[1]salary allocation'!J10 -> 1 | K10: =SUM(E10:J10) -> 1 | M10: 100% MOET | N10: 12024 | O10: =SUMIFS('[1]C&G Ledger_allocation'!AP:AP,'[1]C&G Ledger_allocation'!$H:$H,'salary allocation-v2'!$D10,'[1]C&G Ledger_allocation'!$A:$A,'salary allocation-v2'!$N10) -> #VALUE! | P10: =SUMIFS('[1]C&G Ledger_allocation'!AQ:AQ,'[1]C&G Ledger_allocation'!$H:$H,'salary allocation-v2'!$D10,'[1]C&G Ledger_allocation'!$A:$A,'salary allocation-v2'!$N10) -> #VALUE! | Q10: =SUMIFS('[1]C&G Ledger_allocation'!AR:AR,'[1]C&G Ledger_allocation'!$H:$H,'salary allocation-v2'!$D10,'[1]C&G Ledger_allocation'!$A:$A,'salary allocation-v2'!$N10) -> #VALUE! | R10: =SUMIFS('[1]C&G Ledger_allocation'!AS:AS,'[1]C&G Ledger_allocation'!$H:$H,'salary allocation-v2'!$D10,'[1]C&G Ledger_allocation'!$A:$A,'salary allocation-v2'!$N10) -> #VALUE! | S10: =SUMIFS('[1]C&G Ledger_allocation'!AT:AT,'[1]C&G Ledger_allocation'!$H:$H,'salary allocation-v2'!$D10,'[1]C&G Ledger_allocation'!$A:$A,'salary allocation-v2'!$N10) -> #VALUE! | T10: =SUMIFS('[1]C&G Ledger_allocation'!AU:AU,'[1]C&G Ledger_allocation'!$H:$H,'salary allocation-v2'!$D10,'[1]C&G Ledger_allocation'!$A:$A,'salary allocation-v2'!$N10) -> #VALUE! | U10: =SUMIFS('[1]C&G Ledger_allocation'!AV:AV,'[1]C&G Ledger_allocation'!$H:$H,'salary allocation-v2'!$D10,'[1]C&G Ledger_allocation'!$A:$A,'salary allocation-v2'!$N10) -> #VALUE! | V10: =SUMIFS('[1]C&G Ledger_allocation'!AW:AW,'[1]C&G Ledger_allocation'!$H:$H,'salary allocation-v2'!$D10,'[1]C&G Ledger_allocation'!$A:$A,'salary allocation-v2'!$N10) -> #VALUE! | W10: =SUMIFS('[1]C&G Ledger_allocation'!AX:AX,'[1]C&G Ledger_allocation'!$H:$H,'salary allocation-v2'!$D10,'[1]C&G Ledger_allocation'!$A:$A,'salary allocation-v2'!$N10) -> #VALUE! | X10: =SUMIFS('[1]C&G Ledger_allocation'!AY:AY,'[1]C&G Ledger_allocation'!$H:$H,'salary allocation-v2'!$D10,'[1]C&G Ledger_allocation'!$A:$A,'salary allocation-v2'!$N10) -> #VALUE! | Y10: =SUMIFS('[1]C&G Ledger_allocation'!AZ:AZ,'[1]C&G Ledger_allocation'!$H:$H,'salary allocation-v2'!$D10,'[1]C&G Ledger_allocation'!$A:$A,'salary allocation-v2'!$N10) -> #VALUE! | Z10: =SUMIFS('[1]C&G Ledger_allocation'!BA:BA,'[1]C&G Ledger_allocation'!$H:$H,'salary allocation-v2'!$D10,'[1]C&G Ledger_allocation'!$A:$A,'salary allocation-v2'!$N10) -> #VALUE! | AA10: =SUMIFS('[1]C&G Ledger_allocation'!BB:BB,'[1]C&G Ledger_allocation'!$H:$H,'salary allocation-v2'!$D10,'[1]C&G Ledger_allocation'!$A:$A,'salary allocation-v2'!$N10) -> #VALUE! | AB10: =SUMIFS('[1]C&G Ledger_allocation'!BC:BC,'[1]C&G Ledger_allocation'!$H:$H,'salary allocation-v2'!$D10,'[1]C&G Ledger_allocation'!$A:$A,'salary allocation-v2'!$N10) -> #VALUE! | AC10: =W10 -> #VALUE! | AD10: =$AC10*E10 -> #VALUE! | AE10: =$AC10*F10 -> #VALUE! | AF10: =$AC10*G10 -> #VALUE! | AG10: =$AC10*H10 -> #VALUE! | AH10: =$AC10*I10 -> #VALUE! | AI10: =$AC10*J10 -> #VALUE! | AJ10: =SUM(AD10:AI10) -> #VALUE! | AK10: =AC10-AJ10 -> #VALUE!
A11: =A10+1 -> 6 | B11: Nguyen Hong Kim | C11: HBC | D11: Hoang Thi Kieu Oanh | E11: 0 | F11: ='[1]salary allocation'!F11 -> 0.2 | G11: ='[1]salary allocation'!G11 -> 0.2 | H11: ='[1]salary allocation'!H11 -> 0.2 | J11: ='[1]salary allocation'!E11+'[1]salary allocation'!J11 -> 0.4 | K11: =SUM(E11:J11) -> 1 | L11: done | M11: 5 | N11: 12024 | O11: =SUMIFS('[1]C&G Ledger_allocation'!AP:AP,'[1]C&G Ledger_allocation'!$H:$H,'salary allocation-v2'!$D11,'[1]C&G Ledger_allocation'!$A:$A,'salary allocation-v2'!$N11) -> #VALUE! | P11: =SUMIFS('[1]C&G Ledger_allocation'!AQ:AQ,'[1]C&G Ledger_allocation'!$H:$H,'salary allocation-v2'!$D11,'[1]C&G Ledger_allocation'!$A:$A,'salary allocation-v2'!$N11) -> #VALUE! | Q11: =SUMIFS('[1]C&G Ledger_allocation'!AR:AR,'[1]C&G Ledger_allocation'!$H:$H,'salary allocation-v2'!$D11,'[1]C&G Ledger_allocation'!$A:$A,'salary allocation-v2'!$N11) -> #VALUE! | R11: =SUMIFS('[1]C&G Ledger_allocation'!AS:AS,'[1]C&G Ledger_allocation'!$H:$H,'salary allocation-v2'!$D11,'[1]C&G Ledger_allocation'!$A:$A,'salary allocation-v2'!$N11) -> #VALUE! | S11: =SUMIFS('[1]C&G Ledger_allocation'!AT:AT,'[1]C&G Ledger_allocation'!$H:$H,'salary allocation-v2'!$D11,'[1]C&G Ledger_allocation'!$A:$A,'salary allocation-v2'!$N11) -> #VALUE! | T11: =SUMIFS('[1]C&G Ledger_allocation'!AU:AU,'[1]C&G Ledger_allocation'!$H:$H,'salary allocation-v2'!$D11,'[1]C&G Ledger_allocation'!$A:$A,'salary allocation-v2'!$N11) -> #VALUE! | U11: =SUMIFS('[1]C&G Ledger_allocation'!AV:AV,'[1]C&G Ledger_allocation'!$H:$H,'salary allocation-v2'!$D11,'[1]C&G Ledger_allocation'!$A:$A,'salary allocation-v2'!$N11) -> #VALUE! | V11: =SUMIFS('[1]C&G Ledger_allocation'!AW:AW,'[1]C&G Ledger_allocation'!$H:$H,'salary allocation-v2'!$D11,'[1]C&G Ledger_allocation'!$A:$A,'salary allocation-v2'!$N11) -> #VALUE! | W11: =SUMIFS('[1]C&G Ledger_allocation'!AX:AX,'[1]C&G Ledger_allocation'!$H:$H,'salary allocation-v2'!$D11,'[1]C&G Ledger_allocation'!$A:$A,'salary allocation-v2'!$N11) -> #VALUE! | X11: =SUMIFS('[1]C&G Ledger_allocation'!AY:AY,'[1]C&G Ledger_allocation'!$H:$H,'salary allocation-v2'!$D11,'[1]C&G Ledger_allocation'!$A:$A,'salary allocation-v2'!$N11) -> #VALUE! | Y11: =SUMIFS('[1]C&G Ledger_allocation'!AZ:AZ,'[1]C&G Ledger_allocation'!$H:$H,'salary allocation-v2'!$D11,'[1]C&G Ledger_allocation'!$A:$A,'salary allocation-v2'!$N11) -> #VALUE! | Z11: =SUMIFS('[1]C&G Ledger_allocation'!BA:BA,'[1]C&G Ledger_allocation'!$H:$H,'salary allocation-v2'!$D11,'[1]C&G Ledger_allocation'!$A:$A,'salary allocation-v2'!$N11) -> #VALUE! | AA11: =SUMIFS('[1]C&G Ledger_allocation'!BB:BB,'[1]C&G Ledger_allocation'!$H:$H,'salary allocation-v2'!$D11,'[1]C&G Ledger_allocation'!$A:$A,'salary allocation-v2'!$N11) -> #VALUE! | AB11: =SUMIFS('[1]C&G Ledger_allocation'!BC:BC,'[1]C&G Ledger_allocation'!$H:$H,'salary allocation-v2'!$D11,'[1]C&G Ledger_allocation'!$A:$A,'salary allocation-v2'!$N11) -> #VALUE! | AC11: =R11 -> #VALUE! | AD11: =$AC11*E11 -> #VALUE! | AE11: =$AC11*F11 -> #VALUE! | AF11: =$AC11*G11 -> #VALUE! | AG11: =$AC11*H11 -> #VALUE! | AH11: =$AC11*I11 -> #VALUE! | AI11: =$AC11*J11 -> #VALUE! | AJ11: =SUM(AD11:AI11) -> #VALUE! | AK11: =AC11-AJ11 -> #VALUE!
A12: =A11+1 -> 7 | B12: Hoang Thi Kieu Oanh | C12: HBC | D12: Phan Doan Kim Nhung | E12: 0 | F12: ='[1]salary allocation'!F12 -> 0.2 | G12: ='[1]salary allocation'!G12 -> 0.2 | H12: ='[1]salary allocation'!H12 -> 0.2 | J12: ='[1]salary allocation'!E12+'[1]salary allocation'!J12 -> 0.4 | K12: =SUM(E12:J12) -> 1 | L12: done | M12: 5 | N12: 12024 | O12: =SUMIFS('[1]C&G Ledger_allocation'!AP:AP,'[1]C&G Ledger_allocation'!$H:$H,'salary allocation-v2'!$D12,'[1]C&G Ledger_allocation'!$A:$A,'salary allocation-v2'!$N12) -> #VALUE! | P12: =SUMIFS('[1]C&G Ledger_allocation'!AQ:AQ,'[1]C&G Ledger_allocation'!$H:$H,'salary allocation-v2'!$D12,'[1]C&G Ledger_allocation'!$A:$A,'salary allocation-v2'!$N12) -> #VALUE! | Q12: =SUMIFS('[1]C&G Ledger_allocation'!AR:AR,'[1]C&G Ledger_allocation'!$H:$H,'salary allocation-v2'!$D12,'[1]C&G Ledger_allocation'!$A:$A,'salary allocation-v2'!$N12) -> #VALUE! | R12: =SUMIFS('[1]C&G Ledger_allocation'!AS:AS,'[1]C&G Ledger_allocation'!$H:$H,'salary allocation-v2'!$D12,'[1]C&G Ledger_allocation'!$A:$A,'salary allocation-v2'!$N12) -> #VALUE! | S12: =SUMIFS('[1]C&G Ledger_allocation'!AT:AT,'[1]C&G Ledger_allocation'!$H:$H,'salary allocation-v2'!$D12,'[1]C&G Ledger_allocation'!$A:$A,'salary allocation-v2'!$N12) -> #VALUE! | T12: =SUMIFS('[1]C&G Ledger_allocation'!AU:AU,'[1]C&G Ledger_allocation'!$H:$H,'salary allocation-v2'!$D12,'[1]C&G Ledger_allocation'!$A:$A,'salary allocation-v2'!$N12) -> #VALUE! | U12: =SUMIFS('[1]C&G Ledger_allocation'!AV:AV,'[1]C&G Ledger_allocation'!$H:$H,'salary allocation-v2'!$D12,'[1]C&G Ledger_allocation'!$A:$A,'salary allocation-v2'!$N12) -> #VALUE! | V12: =SUMIFS('[1]C&G Ledger_allocation'!AW:AW,'[1]C&G Ledger_allocation'!$H:$H,'salary allocation-v2'!$D12,'[1]C&G Ledger_allocation'!$A:$A,'salary allocation-v2'!$N12) -> #VALUE! | W12: =SUMIFS('[1]C&G Ledger_allocation'!AX:AX,'[1]C&G Ledger_allocation'!$H:$H,'salary allocation-v2'!$D12,'[1]C&G Ledger_allocation'!$A:$A,'salary allocation-v2'!$N12) -> #VALUE! | X12: =SUMIFS('[1]C&G Ledger_allocation'!AY:AY,'[1]C&G Ledger_allocation'!$H:$H,'salary allocation-v2'!$D12,'[1]C&G Ledger_allocation'!$A:$A,'salary allocation-v2'!$N12) -> #VALUE! | Y12: =SUMIFS('[1]C&G Ledger_allocation'!AZ:AZ,'[1]C&G Ledger_allocation'!$H:$H,'salary allocation-v2'!$D12,'[1]C&G Ledger_allocation'!$A:$A,'salary allocation-v2'!$N12) -> #VALUE! | Z12: =SUMIFS('[1]C&G Ledger_allocation'!BA:BA,'[1]C&G Ledger_allocation'!$H:$H,'salary allocation-v2'!$D12,'[1]C&G Ledger_allocation'!$A:$A,'salary allocation-v2'!$N12) -> #VALUE! | AA12: =SUMIFS('[1]C&G Ledger_allocation'!BB:BB,'[1]C&G Ledger_allocation'!$H:$H,'salary allocation-v2'!$D12,'[1]C&G Ledger_allocation'!$A:$A,'salary allocation-v2'!$N12) -> #VALUE! | AB12: =SUMIFS('[1]C&G Ledger_allocation'!BC:BC,'[1]C&G Ledger_allocation'!$H:$H,'salary allocation-v2'!$D12,'[1]C&G Ledger_allocation'!$A:$A,'salary allocation-v2'!$N12) -> #VALUE! | AC12: =R12 -> #VALUE! | AD12: =$AC12*E12 -> #VALUE! | AE12: =$AC12*F12 -> #VALUE! | AF12: =$AC12*G12 -> #VALUE! | AG12: =$AC12*H12 -> #VALUE! | AH12: =$AC12*I12 -> #VALUE! | AI12: =$AC12*J12 -> #VALUE! | AJ12: =SUM(AD12:AI12) -> #VALUE! | AK12: =AC12-AJ12 -> #VALUE!
A13: =A12+1 -> 8 | B13: Phan Doan Kim Nhung | C13: MOET | D13: Le Thi Thu Huyen | E13: 0 | F13: ='[1]salary allocation'!F13 -> 0.2 | G13: ='[1]salary allocation'!G13 -> 0.2 | H13: ='[1]salary allocation'!H13 -> 0.2 | J13: ='[1]salary allocation'!E13+'[1]salary allocation'!J13 -> 0.4 | K13: =SUM(E13:J13) -> 1 | M13: 5 | N13: 12024 | O13: =SUMIFS('[1]C&G Ledger_allocation'!AP:AP,'[1]C&G Ledger_allocation'!$H:$H,'salary allocation-v2'!$D13,'[1]C&G Ledger_allocation'!$A:$A,'salary allocation-v2'!$N13) -> #VALUE! | P13: =SUMIFS('[1]C&G Ledger_allocation'!AQ:AQ,'[1]C&G Ledger_allocation'!$H:$H,'salary allocation-v2'!$D13,'[1]C&G Ledger_allocation'!$A:$A,'salary allocation-v2'!$N13) -> #VALUE! | Q13: =SUMIFS('[1]C&G Ledger_allocation'!AR:AR,'[1]C&G Ledger_allocation'!$H:$H,'salary allocation-v2'!$D13,'[1]C&G Ledger_allocation'!$A:$A,'salary allocation-v2'!$N13) -> #VALUE! | R13: =SUMIFS('[1]C&G Ledger_allocation'!AS:AS,'[1]C&G Ledger_allocation'!$H:$H,'salary allocation-v2'!$D13,'[1]C&G Ledger_allocation'!$A:$A,'salary allocation-v2'!$N13) -> #VALUE! | S13: =SUMIFS('[1]C&G Ledger_allocation'!AT:AT,'[1]C&G Ledger_allocation'!$H:$H,'salary allocation-v2'!$D13,'[1]C&G Ledger_allocation'!$A:$A,'salary allocation-v2'!$N13) -> #VALUE! | T13: =SUMIFS('[1]C&G Ledger_allocation'!AU:AU,'[1]C&G Ledger_allocation'!$H:$H,'salary allocation-v2'!$D13,'[1]C&G Ledger_allocation'!$A:$A,'salary allocation-v2'!$N13) -> #VALUE! | U13: =SUMIFS('[1]C&G Ledger_allocation'!AV:AV,'[1]C&G Ledger_allocation'!$H:$H,'salary allocation-v2'!$D13,'[1]C&G Ledger_allocation'!$A:$A,'salary allocation-v2'!$N13) -> #VALUE! | V13: =SUMIFS('[1]C&G Ledger_allocation'!AW:AW,'[1]C&G Ledger_allocation'!$H:$H,'salary allocation-v2'!$D13,'[1]C&G Ledger_allocation'!$A:$A,'salary allocation-v2'!$N13) -> #VALUE! | W13: =SUMIFS('[1]C&G Ledger_allocation'!AX:AX,'[1]C&G Ledger_allocation'!$H:$H,'salary allocation-v2'!$D13,'[1]C&G Ledger_allocation'!$A:$A,'salary allocation-v2'!$N13) -> #VALUE! | X13: =SUMIFS('[1]C&G Ledger_allocation'!AY:AY,'[1]C&G Ledger_allocation'!$H:$H,'salary allocation-v2'!$D13,'[1]C&G Ledger_allocation'!$A:$A,'salary allocation-v2'!$N13) -> #VALUE! | Y13: =SUMIFS('[1]C&G Ledger_allocation'!AZ:AZ,'[1]C&G Ledger_allocation'!$H:$H,'salary allocation-v2'!$D13,'[1]C&G Ledger_allocation'!$A:$A,'salary allocation-v2'!$N13) -> #VALUE! | Z13: =SUMIFS('[1]C&G Ledger_allocation'!BA:BA,'[1]C&G Ledger_allocation'!$H:$H,'salary allocation-v2'!$D13,'[1]C&G Ledger_allocation'!$A:$A,'salary allocation-v2'!$N13) -> #VALUE! | AA13: =SUMIFS('[1]C&G Ledger_allocation'!BB:BB,'[1]C&G Ledger_allocation'!$H:$H,'salary allocation-v2'!$D13,'[1]C&G Ledger_allocation'!$A:$A,'salary allocation-v2'!$N13) -> #VALUE! | AB13: =SUMIFS('[1]C&G Ledger_allocation'!BC:BC,'[1]C&G Ledger_allocation'!$H:$H,'salary allocation-v2'!$D13,'[1]C&G Ledger_allocation'!$A:$A,'salary allocation-v2'!$N13) -> #VALUE! | AC13: =W13 -> #VALUE! | AD13: =$AC13*E13 -> #VALUE! | AE13: =$AC13*F13 -> #VALUE! | AF13: =$AC13*G13 -> #VALUE! | AG13: =$AC13*H13 -> #VALUE! | AH13: =$AC13*I13 -> #VALUE! | AI13: =$AC13*J13 -> #VALUE! | AJ13: =SUM(AD13:AI13) -> #VALUE! | AK13: =AC13-AJ13 -> #VALUE!
A14: =A13+1 -> 9 | B14: Pham Thi Dieu Loan | C14: Support | D14: Thuy Thi Bich Thuy Tran | E14: 0.5 | F14: ='[1]salary allocation'!F14 -> 0.1 | G14: ='[1]salary allocation'!G14 -> 0.1 | H14: ='[1]salary allocation'!H14 -> 0.1 | J14: 0.2 | K14: =SUM(E14:J14) -> 1 | M14: 5 | N14: 12024 | O14: =SUMIFS('[1]C&G Ledger_allocation'!AP:AP,'[1]C&G Ledger_allocation'!$H:$H,'salary allocation-v2'!$D14,'[1]C&G Ledger_allocation'!$A:$A,'salary allocation-v2'!$N14) -> #VALUE! | P14: =SUMIFS('[1]C&G Ledger_allocation'!AQ:AQ,'[1]C&G Ledger_allocation'!$H:$H,'salary allocation-v2'!$D14,'[1]C&G Ledger_allocation'!$A:$A,'salary allocation-v2'!$N14) -> #VALUE! | Q14: =SUMIFS('[1]C&G Ledger_allocation'!AR:AR,'[1]C&G Ledger_allocation'!$H:$H,'salary allocation-v2'!$D14,'[1]C&G Ledger_allocation'!$A:$A,'salary allocation-v2'!$N14) -> #VALUE! | R14: =SUMIFS('[1]C&G Ledger_allocation'!AS:AS,'[1]C&G Ledger_allocation'!$H:$H,'salary allocation-v2'!$D14,'[1]C&G Ledger_allocation'!$A:$A,'salary allocation-v2'!$N14) -> #VALUE! | S14: =SUMIFS('[1]C&G Ledger_allocation'!AT:AT,'[1]C&G Ledger_allocation'!$H:$H,'salary allocation-v2'!$D14,'[1]C&G Ledger_allocation'!$A:$A,'salary allocation-v2'!$N14) -> #VALUE! | T14: =SUMIFS('[1]C&G Ledger_allocation'!AU:AU,'[1]C&G Ledger_allocation'!$H:$H,'salary allocation-v2'!$D14,'[1]C&G Ledger_allocation'!$A:$A,'salary allocation-v2'!$N14) -> #VALUE! | U14: =SUMIFS('[1]C&G Ledger_allocation'!AV:AV,'[1]C&G Ledger_allocation'!$H:$H,'salary allocation-v2'!$D14,'[1]C&G Ledger_allocation'!$A:$A,'salary allocation-v2'!$N14) -> #VALUE! | V14: =SUMIFS('[1]C&G Ledger_allocation'!AW:AW,'[1]C&G Ledger_allocation'!$H:$H,'salary allocation-v2'!$D14,'[1]C&G Ledger_allocation'!$A:$A,'salary allocation-v2'!$N14) -> #VALUE! | W14: =SUMIFS('[1]C&G Ledger_allocation'!AX:AX,'[1]C&G Ledger_allocation'!$H:$H,'salary allocation-v2'!$D14,'[1]C&G Ledger_allocation'!$A:$A,'salary allocation-v2'!$N14) -> #VALUE! | X14: =SUMIFS('[1]C&G Ledger_allocation'!AY:AY,'[1]C&G Ledger_allocation'!$H:$H,'salary allocation-v2'!$D14,'[1]C&G Ledger_allocation'!$A:$A,'salary allocation-v2'!$N14) -> #VALUE! | Y14: =SUMIFS('[1]C&G Ledger_allocation'!AZ:AZ,'[1]C&G Ledger_allocation'!$H:$H,'salary allocation-v2'!$D14,'[1]C&G Ledger_allocation'!$A:$A,'salary allocation-v2'!$N14) -> #VALUE! | Z14: =SUMIFS('[1]C&G Ledger_allocation'!BA:BA,'[1]C&G Ledger_allocation'!$H:$H,'salary allocation-v2'!$D14,'[1]C&G Ledger_allocation'!$A:$A,'salary allocation-v2'!$N14) -> #VALUE! | AA14: =SUMIFS('[1]C&G Ledger_allocation'!BB:BB,'[1]C&G Ledger_allocation'!$H:$H,'salary allocation-v2'!$D14,'[1]C&G Ledger_allocation'!$A:$A,'salary allocation-v2'!$N14) -> #VALUE! | AB14: =SUMIFS('[1]C&G Ledger_allocation'!BC:BC,'[1]C&G Ledger_allocation'!$H:$H,'salary allocation-v2'!$D14,'[1]C&G Ledger_allocation'!$A:$A,'salary allocation-v2'!$N14) -> #VALUE! | AC14: =Q14 -> #VALUE! | AD14: =$AC14*E14 -> #VALUE! | AE14: =$AC14*F14 -> #VALUE! | AF14: =$AC14*G14 -> #VALUE! | AG14: =$AC14*H14 -> #VALUE! | AH14: =$AC14*I14 -> #VALUE! | AI14: =$AC14*J14 -> #VALUE! | AJ14: =SUM(AD14:AI14) -> #VALUE! | AK14: =AC14-AJ14 -> #VALUE!
A15: =A14+1 -> 10 | B15: Dang Thanh Canh | C15: Support | D15: Maggie Huyen Nguyen | E15: 0 | F15: ='[1]salary allocation'!F15 -> 0.17 | G15: ='[1]salary allocation'!G15 -> 0.17 | H15: ='[1]salary allocation'!H15 -> 0.17 | J15: ='[1]salary allocation'!E15+'[1]salary allocation'!J15 -> 0.49 | K15: =SUM(E15:J15) -> 1 | M15: 6 | N15: 12024 | O15: =SUMIFS('[1]C&G Ledger_allocation'!AP:AP,'[1]C&G Ledger_allocation'!$H:$H,'salary allocation-v2'!$D15,'[1]C&G Ledger_allocation'!$A:$A,'salary allocation-v2'!$N15) -> #VALUE! | P15: =SUMIFS('[1]C&G Ledger_allocation'!AQ:AQ,'[1]C&G Ledger_allocation'!$H:$H,'salary allocation-v2'!$D15,'[1]C&G Ledger_allocation'!$A:$A,'salary allocation-v2'!$N15) -> #VALUE! | Q15: =SUMIFS('[1]C&G Ledger_allocation'!AR:AR,'[1]C&G Ledger_allocation'!$H:$H,'salary allocation-v2'!$D15,'[1]C&G Ledger_allocation'!$A:$A,'salary allocation-v2'!$N15) -> #VALUE! | R15: =SUMIFS('[1]C&G Ledger_allocation'!AS:AS,'[1]C&G Ledger_allocation'!$H:$H,'salary allocation-v2'!$D15,'[1]C&G Ledger_allocation'!$A:$A,'salary allocation-v2'!$N15) -> #VALUE! | S15: =SUMIFS('[1]C&G Ledger_allocation'!AT:AT,'[1]C&G Ledger_allocation'!$H:$H,'salary allocation-v2'!$D15,'[1]C&G Ledger_allocation'!$A:$A,'salary allocation-v2'!$N15) -> #VALUE! | T15: =SUMIFS('[1]C&G Ledger_allocation'!AU:AU,'[1]C&G Ledger_allocation'!$H:$H,'salary allocation-v2'!$D15,'[1]C&G Ledger_allocation'!$A:$A,'salary allocation-v2'!$N15) -> #VALUE! | U15: =SUMIFS('[1]C&G Ledger_allocation'!AV:AV,'[1]C&G Ledger_allocation'!$H:$H,'salary allocation-v2'!$D15,'[1]C&G Ledger_allocation'!$A:$A,'salary allocation-v2'!$N15) -> #VALUE! | V15: =SUMIFS('[1]C&G Ledger_allocation'!AW:AW,'[1]C&G Ledger_allocation'!$H:$H,'salary allocation-v2'!$D15,'[1]C&G Ledger_allocation'!$A:$A,'salary allocation-v2'!$N15) -> #VALUE! | W15: =SUMIFS('[1]C&G Ledger_allocation'!AX:AX,'[1]C&G Ledger_allocation'!$H:$H,'salary allocation-v2'!$D15,'[1]C&G Ledger_allocation'!$A:$A,'salary allocation-v2'!$N15) -> #VALUE! | X15: =SUMIFS('[1]C&G Ledger_allocation'!AY:AY,'[1]C&G Ledger_allocation'!$H:$H,'salary allocation-v2'!$D15,'[1]C&G Ledger_allocation'!$A:$A,'salary allocation-v2'!$N15) -> #VALUE! | Y15: =SUMIFS('[1]C&G Ledger_allocation'!AZ:AZ,'[1]C&G Ledger_allocation'!$H:$H,'salary allocation-v2'!$D15,'[1]C&G Ledger_allocation'!$A:$A,'salary allocation-v2'!$N15) -> #VALUE! | Z15: =SUMIFS('[1]C&G Ledger_allocation'!BA:BA,'[1]C&G Ledger_allocation'!$H:$H,'salary allocation-v2'!$D15,'[1]C&G Ledger_allocation'!$A:$A,'salary allocation-v2'!$N15) -> #VALUE! | AA15: =SUMIFS('[1]C&G Ledger_allocation'!BB:BB,'[1]C&G Ledger_allocation'!$H:$H,'salary allocation-v2'!$D15,'[1]C&G Ledger_allocation'!$A:$A,'salary allocation-v2'!$N15) -> #VALUE! | AB15: =SUMIFS('[1]C&G Ledger_allocation'!BC:BC,'[1]C&G Ledger_allocation'!$H:$H,'salary allocation-v2'!$D15,'[1]C&G Ledger_allocation'!$A:$A,'salary allocation-v2'!$N15) -> #VALUE! | AC15: =Q15 -> #VALUE! | AD15: =$AC15*E15 -> #VALUE! | AE15: =$AC15*F15 -> #VALUE! | AF15: =$AC15*G15 -> #VALUE! | AG15: =$AC15*H15 -> #VALUE! | AH15: =$AC15*I15 -> #VALUE! | AI15: =$AC15*J15 -> #VALUE! | AJ15: =SUM(AD15:AI15) -> #VALUE! | AK15: =AC15-AJ15 -> #VALUE!
A16: =A15+1 -> 11 | B16: Alice Do Kim Dung | C16: Support | D16: Nguyen Hong Kim | E16: 0 | F16: ='[1]salary allocation'!F16 -> 0.1 | G16: ='[1]salary allocation'!G16 -> 0.1 | H16: ='[1]salary allocation'!H16 -> 0.1 | J16: ='[1]salary allocation'!E16+'[1]salary allocation'!J16 -> 0.7 | K16: =SUM(E16:J16) -> 1 | M16: 5 | N16: 12024 | O16: =SUMIFS('[1]C&G Ledger_allocation'!AP:AP,'[1]C&G Ledger_allocation'!$H:$H,'salary allocation-v2'!$D16,'[1]C&G Ledger_allocation'!$A:$A,'salary allocation-v2'!$N16) -> #VALUE! | P16: =SUMIFS('[1]C&G Ledger_allocation'!AQ:AQ,'[1]C&G Ledger_allocation'!$H:$H,'salary allocation-v2'!$D16,'[1]C&G Ledger_allocation'!$A:$A,'salary allocation-v2'!$N16) -> #VALUE! | Q16: =SUMIFS('[1]C&G Ledger_allocation'!AR:AR,'[1]C&G Ledger_allocation'!$H:$H,'salary allocation-v2'!$D16,'[1]C&G Ledger_allocation'!$A:$A,'salary allocation-v2'!$N16) -> #VALUE! | R16: =SUMIFS('[1]C&G Ledger_allocation'!AS:AS,'[1]C&G Ledger_allocation'!$H:$H,'salary allocation-v2'!$D16,'[1]C&G Ledger_allocation'!$A:$A,'salary allocation-v2'!$N16) -> #VALUE! | S16: =SUMIFS('[1]C&G Ledger_allocation'!AT:AT,'[1]C&G Ledger_allocation'!$H:$H,'salary allocation-v2'!$D16,'[1]C&G Ledger_allocation'!$A:$A,'salary allocation-v2'!$N16) -> #VALUE! | T16: =SUMIFS('[1]C&G Ledger_allocation'!AU:AU,'[1]C&G Ledger_allocation'!$H:$H,'salary allocation-v2'!$D16,'[1]C&G Ledger_allocation'!$A:$A,'salary allocation-v2'!$N16) -> #VALUE! | U16: =SUMIFS('[1]C&G Ledger_allocation'!AV:AV,'[1]C&G Ledger_allocation'!$H:$H,'salary allocation-v2'!$D16,'[1]C&G Ledger_allocation'!$A:$A,'salary allocation-v2'!$N16) -> #VALUE! | V16: =SUMIFS('[1]C&G Ledger_allocation'!AW:AW,'[1]C&G Ledger_allocation'!$H:$H,'salary allocation-v2'!$D16,'[1]C&G Ledger_allocation'!$A:$A,'salary allocation-v2'!$N16) -> #VALUE! | W16: =SUMIFS('[1]C&G Ledger_allocation'!AX:AX,'[1]C&G Ledger_allocation'!$H:$H,'salary allocation-v2'!$D16,'[1]C&G Ledger_allocation'!$A:$A,'salary allocation-v2'!$N16) -> #VALUE! | X16: =SUMIFS('[1]C&G Ledger_allocation'!AY:AY,'[1]C&G Ledger_allocation'!$H:$H,'salary allocation-v2'!$D16,'[1]C&G Ledger_allocation'!$A:$A,'salary allocation-v2'!$N16) -> #VALUE! | Y16: =SUMIFS('[1]C&G Ledger_allocation'!AZ:AZ,'[1]C&G Ledger_allocation'!$H:$H,'salary allocation-v2'!$D16,'[1]C&G Ledger_allocation'!$A:$A,'salary allocation-v2'!$N16) -> #VALUE! | Z16: =SUMIFS('[1]C&G Ledger_allocation'!BA:BA,'[1]C&G Ledger_allocation'!$H:$H,'salary allocation-v2'!$D16,'[1]C&G Ledger_allocation'!$A:$A,'salary allocation-v2'!$N16) -> #VALUE! | AA16: =SUMIFS('[1]C&G Ledger_allocation'!BB:BB,'[1]C&G Ledger_allocation'!$H:$H,'salary allocation-v2'!$D16,'[1]C&G Ledger_allocation'!$A:$A,'salary allocation-v2'!$N16) -> #VALUE! | AB16: =SUMIFS('[1]C&G Ledger_allocation'!BC:BC,'[1]C&G Ledger_allocation'!$H:$H,'salary allocation-v2'!$D16,'[1]C&G Ledger_allocation'!$A:$A,'salary allocation-v2'!$N16) -> #VALUE! | AC16: =Q16 -> #VALUE! | AD16: =$AC16*E16 -> #VALUE! | AE16: =$AC16*F16 -> #VALUE! | AF16: =$AC16*G16 -> #VALUE! | AG16: =$AC16*H16 -> #VALUE! | AH16: =$AC16*I16 -> #VALUE! | AI16: =$AC16*J16 -> #VALUE! | AJ16: =SUM(AD16:AI16) -> #VALUE! | AK16: =AC16-AJ16 -> #VALUE!
A17: =A16+1 -> 12 | B17: Truong Thi Hai | C17: Support | D17: Dang Thanh Canh | E17: 0 | F17: ='[1]salary allocation'!F17 -> 0.17 | G17: ='[1]salary allocation'!G17 -> 0.17 | H17: ='[1]salary allocation'!H17 -> 0.17 | J17: ='[1]salary allocation'!E17+'[1]salary allocation'!J17 -> 0.49 | K17: =SUM(E17:J17) -> 1 | M17: 6 | N17: 12024 | O17: =SUMIFS('[1]C&G Ledger_allocation'!AP:AP,'[1]C&G Ledger_allocation'!$H:$H,'salary allocation-v2'!$D17,'[1]C&G Ledger_allocation'!$A:$A,'salary allocation-v2'!$N17) -> #VALUE! | P17: =SUMIFS('[1]C&G Ledger_allocation'!AQ:AQ,'[1]C&G Ledger_allocation'!$H:$H,'salary allocation-v2'!$D17,'[1]C&G Ledger_allocation'!$A:$A,'salary allocation-v2'!$N17) -> #VALUE! | Q17: =SUMIFS('[1]C&G Ledger_allocation'!AR:AR,'[1]C&G Ledger_allocation'!$H:$H,'salary allocation-v2'!$D17,'[1]C&G Ledger_allocation'!$A:$A,'salary allocation-v2'!$N17) -> #VALUE! | R17: =SUMIFS('[1]C&G Ledger_allocation'!AS:AS,'[1]C&G Ledger_allocation'!$H:$H,'salary allocation-v2'!$D17,'[1]C&G Ledger_allocation'!$A:$A,'salary allocation-v2'!$N17) -> #VALUE! | S17: =SUMIFS('[1]C&G Ledger_allocation'!AT:AT,'[1]C&G Ledger_allocation'!$H:$H,'salary allocation-v2'!$D17,'[1]C&G Ledger_allocation'!$A:$A,'salary allocation-v2'!$N17) -> #VALUE! | T17: =SUMIFS('[1]C&G Ledger_allocation'!AU:AU,'[1]C&G Ledger_allocation'!$H:$H,'salary allocation-v2'!$D17,'[1]C&G Ledger_allocation'!$A:$A,'salary allocation-v2'!$N17) -> #VALUE! | U17: =SUMIFS('[1]C&G Ledger_allocation'!AV:AV,'[1]C&G Ledger_allocation'!$H:$H,'salary allocation-v2'!$D17,'[1]C&G Ledger_allocation'!$A:$A,'salary allocation-v2'!$N17) -> #VALUE! | V17: =SUMIFS('[1]C&G Ledger_allocation'!AW:AW,'[1]C&G Ledger_allocation'!$H:$H,'salary allocation-v2'!$D17,'[1]C&G Ledger_allocation'!$A:$A,'salary allocation-v2'!$N17) -> #VALUE! | W17: =SUMIFS('[1]C&G Ledger_allocation'!AX:AX,'[1]C&G Ledger_allocation'!$H:$H,'salary allocation-v2'!$D17,'[1]C&G Ledger_allocation'!$A:$A,'salary allocation-v2'!$N17) -> #VALUE! | X17: =SUMIFS('[1]C&G Ledger_allocation'!AY:AY,'[1]C&G Ledger_allocation'!$H:$H,'salary allocation-v2'!$D17,'[1]C&G Ledger_allocation'!$A:$A,'salary allocation-v2'!$N17) -> #VALUE! | Y17: =SUMIFS('[1]C&G Ledger_allocation'!AZ:AZ,'[1]C&G Ledger_allocation'!$H:$H,'salary allocation-v2'!$D17,'[1]C&G Ledger_allocation'!$A:$A,'salary allocation-v2'!$N17) -> #VALUE! | Z17: =SUMIFS('[1]C&G Ledger_allocation'!BA:BA,'[1]C&G Ledger_allocation'!$H:$H,'salary allocation-v2'!$D17,'[1]C&G Ledger_allocation'!$A:$A,'salary allocation-v2'!$N17) -> #VALUE! | AA17: =SUMIFS('[1]C&G Ledger_allocation'!BB:BB,'[1]C&G Ledger_allocation'!$H:$H,'salary allocation-v2'!$D17,'[1]C&G Ledger_allocation'!$A:$A,'salary allocation-v2'!$N17) -> #VALUE! | AB17: =SUMIFS('[1]C&G Ledger_allocation'!BC:BC,'[1]C&G Ledger_allocation'!$H:$H,'salary allocation-v2'!$D17,'[1]C&G Ledger_allocation'!$A:$A,'salary allocation-v2'!$N17) -> #VALUE! | AC17: =Q17 -> #VALUE! | AD17: =$AC17*E17 -> #VALUE! | AE17: =$AC17*F17 -> #VALUE! | AF17: =$AC17*G17 -> #VALUE! | AG17: =$AC17*H17 -> #VALUE! | AH17: =$AC17*I17 -> #VALUE! | AI17: =$AC17*J17 -> #VALUE! | AJ17: =SUM(AD17:AI17) -> #VALUE! | AK17: =AC17-AJ17 -> #VALUE!
A18: =A17+1 -> 13 | B18: Le Thi Thu Huyen | C18: Support | D18: Nguyen Thi Thanh Thanh | E18: 0 | F18: ='[1]salary allocation'!F18 -> 0.17 | G18: ='[1]salary allocation'!G18 -> 0.17 | H18: ='[1]salary allocation'!H18 -> 0.17 | J18: ='[1]salary allocation'!E18+'[1]salary allocation'!J18 -> 0.49 | K18: =SUM(E18:J18) -> 1 | M18: 6 | N18: 12024 | O18: =SUMIFS('[1]C&G Ledger_allocation'!AP:AP,'[1]C&G Ledger_allocation'!$H:$H,'salary allocation-v2'!$D18,'[1]C&G Ledger_allocation'!$A:$A,'salary allocation-v2'!$N18) -> #VALUE! | P18: =SUMIFS('[1]C&G Ledger_allocation'!AQ:AQ,'[1]C&G Ledger_allocation'!$H:$H,'salary allocation-v2'!$D18,'[1]C&G Ledger_allocation'!$A:$A,'salary allocation-v2'!$N18) -> #VALUE! | Q18: =SUMIFS('[1]C&G Ledger_allocation'!AR:AR,'[1]C&G Ledger_allocation'!$H:$H,'salary allocation-v2'!$D18,'[1]C&G Ledger_allocation'!$A:$A,'salary allocation-v2'!$N18) -> #VALUE! | R18: =SUMIFS('[1]C&G Ledger_allocation'!AS:AS,'[1]C&G Ledger_allocation'!$H:$H,'salary allocation-v2'!$D18,'[1]C&G Ledger_allocation'!$A:$A,'salary allocation-v2'!$N18) -> #VALUE! | S18: =SUMIFS('[1]C&G Ledger_allocation'!AT:AT,'[1]C&G Ledger_allocation'!$H:$H,'salary allocation-v2'!$D18,'[1]C&G Ledger_allocation'!$A:$A,'salary allocation-v2'!$N18) -> #VALUE! | T18: =SUMIFS('[1]C&G Ledger_allocation'!AU:AU,'[1]C&G Ledger_allocation'!$H:$H,'salary allocation-v2'!$D18,'[1]C&G Ledger_allocation'!$A:$A,'salary allocation-v2'!$N18) -> #VALUE! | U18: =SUMIFS('[1]C&G Ledger_allocation'!AV:AV,'[1]C&G Ledger_allocation'!$H:$H,'salary allocation-v2'!$D18,'[1]C&G Ledger_allocation'!$A:$A,'salary allocation-v2'!$N18) -> #VALUE! | V18: =SUMIFS('[1]C&G Ledger_allocation'!AW:AW,'[1]C&G Ledger_allocation'!$H:$H,'salary allocation-v2'!$D18,'[1]C&G Ledger_allocation'!$A:$A,'salary allocation-v2'!$N18) -> #VALUE! | W18: =SUMIFS('[1]C&G Ledger_allocation'!AX:AX,'[1]C&G Ledger_allocation'!$H:$H,'salary allocation-v2'!$D18,'[1]C&G Ledger_allocation'!$A:$A,'salary allocation-v2'!$N18) -> #VALUE! | X18: =SUMIFS('[1]C&G Ledger_allocation'!AY:AY,'[1]C&G Ledger_allocation'!$H:$H,'salary allocation-v2'!$D18,'[1]C&G Ledger_allocation'!$A:$A,'salary allocation-v2'!$N18) -> #VALUE! | Y18: =SUMIFS('[1]C&G Ledger_allocation'!AZ:AZ,'[1]C&G Ledger_allocation'!$H:$H,'salary allocation-v2'!$D18,'[1]C&G Ledger_allocation'!$A:$A,'salary allocation-v2'!$N18) -> #VALUE! | Z18: =SUMIFS('[1]C&G Ledger_allocation'!BA:BA,'[1]C&G Ledger_allocation'!$H:$H,'salary allocation-v2'!$D18,'[1]C&G Ledger_allocation'!$A:$A,'salary allocation-v2'!$N18) -> #VALUE! | AA18: =SUMIFS('[1]C&G Ledger_allocation'!BB:BB,'[1]C&G Ledger_allocation'!$H:$H,'salary allocation-v2'!$D18,'[1]C&G Ledger_allocation'!$A:$A,'salary allocation-v2'!$N18) -> #VALUE! | AB18: =SUMIFS('[1]C&G Ledger_allocation'!BC:BC,'[1]C&G Ledger_allocation'!$H:$H,'salary allocation-v2'!$D18,'[1]C&G Ledger_allocation'!$A:$A,'salary allocation-v2'!$N18) -> #VALUE! | AC18: =Q18 -> #VALUE! | AD18: =$AC18*E18 -> #VALUE! | AE18: =$AC18*F18 -> #VALUE! | AF18: =$AC18*G18 -> #VALUE! | AG18: =$AC18*H18 -> #VALUE! | AH18: =$AC18*I18 -> #VALUE! | AI18: =$AC18*J18 -> #VALUE! | AJ18: =SUM(AD18:AI18) -> #VALUE! | AK18: =AC18-AJ18 -> #VALUE!
A19: =A18+1 -> 14 | B19: Huynh My Ngoc | C19: Support | D19: Phan Thi Thao Nguyen | E19: 0 | F19: ='[1]salary allocation'!F19 -> 0.17 | G19: ='[1]salary allocation'!G19 -> 0.17 | H19: ='[1]salary allocation'!H19 -> 0.17 | J19: ='[1]salary allocation'!E19+'[1]salary allocation'!J19 -> 0.49 | K19: =SUM(E19:J19) -> 1 | M19: 6 | N19: 12024 | O19: =SUMIFS('[1]C&G Ledger_allocation'!AP:AP,'[1]C&G Ledger_allocation'!$H:$H,'salary allocation-v2'!$D19,'[1]C&G Ledger_allocation'!$A:$A,'salary allocation-v2'!$N19) -> #VALUE! | P19: =SUMIFS('[1]C&G Ledger_allocation'!AQ:AQ,'[1]C&G Ledger_allocation'!$H:$H,'salary allocation-v2'!$D19,'[1]C&G Ledger_allocation'!$A:$A,'salary allocation-v2'!$N19) -> #VALUE! | Q19: =SUMIFS('[1]C&G Ledger_allocation'!AR:AR,'[1]C&G Ledger_allocation'!$H:$H,'salary allocation-v2'!$D19,'[1]C&G Ledger_allocation'!$A:$A,'salary allocation-v2'!$N19) -> #VALUE! | R19: =SUMIFS('[1]C&G Ledger_allocation'!AS:AS,'[1]C&G Ledger_allocation'!$H:$H,'salary allocation-v2'!$D19,'[1]C&G Ledger_allocation'!$A:$A,'salary allocation-v2'!$N19) -> #VALUE! | S19: =SUMIFS('[1]C&G Ledger_allocation'!AT:AT,'[1]C&G Ledger_allocation'!$H:$H,'salary allocation-v2'!$D19,'[1]C&G Ledger_allocation'!$A:$A,'salary allocation-v2'!$N19) -> #VALUE! | T19: =SUMIFS('[1]C&G Ledger_allocation'!AU:AU,'[1]C&G Ledger_allocation'!$H:$H,'salary allocation-v2'!$D19,'[1]C&G Ledger_allocation'!$A:$A,'salary allocation-v2'!$N19) -> #VALUE! | U19: =SUMIFS('[1]C&G Ledger_allocation'!AV:AV,'[1]C&G Ledger_allocation'!$H:$H,'salary allocation-v2'!$D19,'[1]C&G Ledger_allocation'!$A:$A,'salary allocation-v2'!$N19) -> #VALUE! | V19: =SUMIFS('[1]C&G Ledger_allocation'!AW:AW,'[1]C&G Ledger_allocation'!$H:$H,'salary allocation-v2'!$D19,'[1]C&G Ledger_allocation'!$A:$A,'salary allocation-v2'!$N19) -> #VALUE! | W19: =SUMIFS('[1]C&G Ledger_allocation'!AX:AX,'[1]C&G Ledger_allocation'!$H:$H,'salary allocation-v2'!$D19,'[1]C&G Ledger_allocation'!$A:$A,'salary allocation-v2'!$N19) -> #VALUE! | X19: =SUMIFS('[1]C&G Ledger_allocation'!AY:AY,'[1]C&G Ledger_allocation'!$H:$H,'salary allocation-v2'!$D19,'[1]C&G Ledger_allocation'!$A:$A,'salary allocation-v2'!$N19) -> #VALUE! | Y19: =SUMIFS('[1]C&G Ledger_allocation'!AZ:AZ,'[1]C&G Ledger_allocation'!$H:$H,'salary allocation-v2'!$D19,'[1]C&G Ledger_allocation'!$A:$A,'salary allocation-v2'!$N19) -> #VALUE! | Z19: =SUMIFS('[1]C&G Ledger_allocation'!BA:BA,'[1]C&G Ledger_allocation'!$H:$H,'salary allocation-v2'!$D19,'[1]C&G Ledger_allocation'!$A:$A,'salary allocation-v2'!$N19) -> #VALUE! | AA19: =SUMIFS('[1]C&G Ledger_allocation'!BB:BB,'[1]C&G Ledger_allocation'!$H:$H,'salary allocation-v2'!$D19,'[1]C&G Ledger_allocation'!$A:$A,'salary allocation-v2'!$N19) -> #VALUE! | AB19: =SUMIFS('[1]C&G Ledger_allocation'!BC:BC,'[1]C&G Ledger_allocation'!$H:$H,'salary allocation-v2'!$D19,'[1]C&G Ledger_allocation'!$A:$A,'salary allocation-v2'!$N19) -> #VALUE! | AC19: =Q19 -> #VALUE! | AD19: =$AC19*E19 -> #VALUE! | AE19: =$AC19*F19 -> #VALUE! | AF19: =$AC19*G19 -> #VALUE! | AG19: =$AC19*H19 -> #VALUE! | AH19: =$AC19*I19 -> #VALUE! | AI19: =$AC19*J19 -> #VALUE! | AJ19: =SUM(AD19:AI19) -> #VALUE! | AK19: =AC19-AJ19 -> #VALUE!
A20: =A19+1 -> 15 | B20: Bui Thi Huong | C20: HBC | D20: Tran Thi Que Chi | E20: 0 | F20: ='[1]salary allocation'!F20 -> 0.2 | G20: ='[1]salary allocation'!G20 -> 0.2 | H20: ='[1]salary allocation'!H20 -> 0.2 | J20: ='[1]salary allocation'!E20+'[1]salary allocation'!J20 -> 0.4 | K20: =SUM(E20:J20) -> 1 | M20: 5 | N20: 12024 | O20: =SUMIFS('[1]C&G Ledger_allocation'!AP:AP,'[1]C&G Ledger_allocation'!$H:$H,'salary allocation-v2'!$D20,'[1]C&G Ledger_allocation'!$A:$A,'salary allocation-v2'!$N20) -> #VALUE! | P20: =SUMIFS('[1]C&G Ledger_allocation'!AQ:AQ,'[1]C&G Ledger_allocation'!$H:$H,'salary allocation-v2'!$D20,'[1]C&G Ledger_allocation'!$A:$A,'salary allocation-v2'!$N20) -> #VALUE! | Q20: =SUMIFS('[1]C&G Ledger_allocation'!AR:AR,'[1]C&G Ledger_allocation'!$H:$H,'salary allocation-v2'!$D20,'[1]C&G Ledger_allocation'!$A:$A,'salary allocation-v2'!$N20) -> #VALUE! | R20: =SUMIFS('[1]C&G Ledger_allocation'!AS:AS,'[1]C&G Ledger_allocation'!$H:$H,'salary allocation-v2'!$D20,'[1]C&G Ledger_allocation'!$A:$A,'salary allocation-v2'!$N20) -> #VALUE! | S20: =SUMIFS('[1]C&G Ledger_allocation'!AT:AT,'[1]C&G Ledger_allocation'!$H:$H,'salary allocation-v2'!$D20,'[1]C&G Ledger_allocation'!$A:$A,'salary allocation-v2'!$N20) -> #VALUE! | T20: =SUMIFS('[1]C&G Ledger_allocation'!AU:AU,'[1]C&G Ledger_allocation'!$H:$H,'salary allocation-v2'!$D20,'[1]C&G Ledger_allocation'!$A:$A,'salary allocation-v2'!$N20) -> #VALUE! | U20: =SUMIFS('[1]C&G Ledger_allocation'!AV:AV,'[1]C&G Ledger_allocation'!$H:$H,'salary allocation-v2'!$D20,'[1]C&G Ledger_allocation'!$A:$A,'salary allocation-v2'!$N20) -> #VALUE! | V20: =SUMIFS('[1]C&G Ledger_allocation'!AW:AW,'[1]C&G Ledger_allocation'!$H:$H,'salary allocation-v2'!$D20,'[1]C&G Ledger_allocation'!$A:$A,'salary allocation-v2'!$N20) -> #VALUE! | W20: =SUMIFS('[1]C&G Ledger_allocation'!AX:AX,'[1]C&G Ledger_allocation'!$H:$H,'salary allocation-v2'!$D20,'[1]C&G Ledger_allocation'!$A:$A,'salary allocation-v2'!$N20) -> #VALUE! | X20: =SUMIFS('[1]C&G Ledger_allocation'!AY:AY,'[1]C&G Ledger_allocation'!$H:$H,'salary allocation-v2'!$D20,'[1]C&G Ledger_allocation'!$A:$A,'salary allocation-v2'!$N20) -> #VALUE! | Y20: =SUMIFS('[1]C&G Ledger_allocation'!AZ:AZ,'[1]C&G Ledger_allocation'!$H:$H,'salary allocation-v2'!$D20,'[1]C&G Ledger_allocation'!$A:$A,'salary allocation-v2'!$N20) -> #VALUE! | Z20: =SUMIFS('[1]C&G Ledger_allocation'!BA:BA,'[1]C&G Ledger_allocation'!$H:$H,'salary allocation-v2'!$D20,'[1]C&G Ledger_allocation'!$A:$A,'salary allocation-v2'!$N20) -> #VALUE! | AA20: =SUMIFS('[1]C&G Ledger_allocation'!BB:BB,'[1]C&G Ledger_allocation'!$H:$H,'salary allocation-v2'!$D20,'[1]C&G Ledger_allocation'!$A:$A,'salary allocation-v2'!$N20) -> #VALUE! | AB20: =SUMIFS('[1]C&G Ledger_allocation'!BC:BC,'[1]C&G Ledger_allocation'!$H:$H,'salary allocation-v2'!$D20,'[1]C&G Ledger_allocation'!$A:$A,'salary allocation-v2'!$N20) -> #VALUE! | AC20: =R20 -> #VALUE! | AD20: =$AC20*E20 -> #VALUE! | AE20: =$AC20*F20 -> #VALUE! | AF20: =$AC20*G20 -> #VALUE! | AG20: =$AC20*H20 -> #VALUE! | AH20: =$AC20*I20 -> #VALUE! | AI20: =$AC20*J20 -> #VALUE! | AJ20: =SUM(AD20:AI20) -> #VALUE! | AK20: =AC20-AJ20 -> #VALUE!
A21: =A20+1 -> 16 | B21: Tran Thi Que Chi | C21: HBC | D21: Pham Thi Dieu Loan | E21: 0 | F21: ='[1]salary allocation'!F21 -> 0.2 | G21: ='[1]salary allocation'!G21 -> 0.2 | H21: ='[1]salary allocation'!H21 -> 0.2 | J21: ='[1]salary allocation'!E21+'[1]salary allocation'!J21 -> 0.4 | K21: =SUM(E21:J21) -> 1 | M21: 5 | N21: 12024 | O21: =SUMIFS('[1]C&G Ledger_allocation'!AP:AP,'[1]C&G Ledger_allocation'!$H:$H,'salary allocation-v2'!$D21,'[1]C&G Ledger_allocation'!$A:$A,'salary allocation-v2'!$N21) -> #VALUE! | P21: =SUMIFS('[1]C&G Ledger_allocation'!AQ:AQ,'[1]C&G Ledger_allocation'!$H:$H,'salary allocation-v2'!$D21,'[1]C&G Ledger_allocation'!$A:$A,'salary allocation-v2'!$N21) -> #VALUE! | Q21: =SUMIFS('[1]C&G Ledger_allocation'!AR:AR,'[1]C&G Ledger_allocation'!$H:$H,'salary allocation-v2'!$D21,'[1]C&G Ledger_allocation'!$A:$A,'salary allocation-v2'!$N21) -> #VALUE! | R21: =SUMIFS('[1]C&G Ledger_allocation'!AS:AS,'[1]C&G Ledger_allocation'!$H:$H,'salary allocation-v2'!$D21,'[1]C&G Ledger_allocation'!$A:$A,'salary allocation-v2'!$N21) -> #VALUE! | S21: =SUMIFS('[1]C&G Ledger_allocation'!AT:AT,'[1]C&G Ledger_allocation'!$H:$H,'salary allocation-v2'!$D21,'[1]C&G Ledger_allocation'!$A:$A,'salary allocation-v2'!$N21) -> #VALUE! | T21: =SUMIFS('[1]C&G Ledger_allocation'!AU:AU,'[1]C&G Ledger_allocation'!$H:$H,'salary allocation-v2'!$D21,'[1]C&G Ledger_allocation'!$A:$A,'salary allocation-v2'!$N21) -> #VALUE! | U21: =SUMIFS('[1]C&G Ledger_allocation'!AV:AV,'[1]C&G Ledger_allocation'!$H:$H,'salary allocation-v2'!$D21,'[1]C&G Ledger_allocation'!$A:$A,'salary allocation-v2'!$N21) -> #VALUE! | V21: =SUMIFS('[1]C&G Ledger_allocation'!AW:AW,'[1]C&G Ledger_allocation'!$H:$H,'salary allocation-v2'!$D21,'[1]C&G Ledger_allocation'!$A:$A,'salary allocation-v2'!$N21) -> #VALUE! | W21: =SUMIFS('[1]C&G Ledger_allocation'!AX:AX,'[1]C&G Ledger_allocation'!$H:$H,'salary allocation-v2'!$D21,'[1]C&G Ledger_allocation'!$A:$A,'salary allocation-v2'!$N21) -> #VALUE! | X21: =SUMIFS('[1]C&G Ledger_allocation'!AY:AY,'[1]C&G Ledger_allocation'!$H:$H,'salary allocation-v2'!$D21,'[1]C&G Ledger_allocation'!$A:$A,'salary allocation-v2'!$N21) -> #VALUE! | Y21: =SUMIFS('[1]C&G Ledger_allocation'!AZ:AZ,'[1]C&G Ledger_allocation'!$H:$H,'salary allocation-v2'!$D21,'[1]C&G Ledger_allocation'!$A:$A,'salary allocation-v2'!$N21) -> #VALUE! | Z21: =SUMIFS('[1]C&G Ledger_allocation'!BA:BA,'[1]C&G Ledger_allocation'!$H:$H,'salary allocation-v2'!$D21,'[1]C&G Ledger_allocation'!$A:$A,'salary allocation-v2'!$N21) -> #VALUE! | AA21: =SUMIFS('[1]C&G Ledger_allocation'!BB:BB,'[1]C&G Ledger_allocation'!$H:$H,'salary allocation-v2'!$D21,'[1]C&G Ledger_allocation'!$A:$A,'salary allocation-v2'!$N21) -> #VALUE! | AB21: =SUMIFS('[1]C&G Ledger_allocation'!BC:BC,'[1]C&G Ledger_allocation'!$H:$H,'salary allocation-v2'!$D21,'[1]C&G Ledger_allocation'!$A:$A,'salary allocation-v2'!$N21) -> #VALUE! | AC21: =R21 -> #VALUE! | AD21: =$AC21*E21 -> #VALUE! | AE21: =$AC21*F21 -> #VALUE! | AF21: =$AC21*G21 -> #VALUE! | AG21: =$AC21*H21 -> #VALUE! | AH21: =$AC21*I21 -> #VALUE! | AI21: =$AC21*J21 -> #VALUE! | AJ21: =SUM(AD21:AI21) -> #VALUE! | AK21: =AC21-AJ21 -> #VALUE!
A22: =A21+1 -> 17 | B22: Phan Thi Thảo Nguyên | C22: ELC | D22: Alice Do Kim Dung | E22: 0 | F22: ='[1]salary allocation'!F22 -> 0 | G22: ='[1]salary allocation'!G22 -> 0 | H22: ='[1]salary allocation'!H22 -> 0 | J22: ='[1]salary allocation'!E22+'[1]salary allocation'!J22 -> 1 | K22: =SUM(E22:J22) -> 1 | M22: 100% ELC | N22: 12024 | O22: =SUMIFS('[1]C&G Ledger_allocation'!AP:AP,'[1]C&G Ledger_allocation'!$H:$H,'salary allocation-v2'!$D22,'[1]C&G Ledger_allocation'!$A:$A,'salary allocation-v2'!$N22) -> #VALUE! | P22: =SUMIFS('[1]C&G Ledger_allocation'!AQ:AQ,'[1]C&G Ledger_allocation'!$H:$H,'salary allocation-v2'!$D22,'[1]C&G Ledger_allocation'!$A:$A,'salary allocation-v2'!$N22) -> #VALUE! | Q22: =SUMIFS('[1]C&G Ledger_allocation'!AR:AR,'[1]C&G Ledger_allocation'!$H:$H,'salary allocation-v2'!$D22,'[1]C&G Ledger_allocation'!$A:$A,'salary allocation-v2'!$N22) -> #VALUE! | R22: =SUMIFS('[1]C&G Ledger_allocation'!AS:AS,'[1]C&G Ledger_allocation'!$H:$H,'salary allocation-v2'!$D22,'[1]C&G Ledger_allocation'!$A:$A,'salary allocation-v2'!$N22) -> #VALUE! | S22: =SUMIFS('[1]C&G Ledger_allocation'!AT:AT,'[1]C&G Ledger_allocation'!$H:$H,'salary allocation-v2'!$D22,'[1]C&G Ledger_allocation'!$A:$A,'salary allocation-v2'!$N22) -> #VALUE! | T22: =SUMIFS('[1]C&G Ledger_allocation'!AU:AU,'[1]C&G Ledger_allocation'!$H:$H,'salary allocation-v2'!$D22,'[1]C&G Ledger_allocation'!$A:$A,'salary allocation-v2'!$N22) -> #VALUE! | U22: =SUMIFS('[1]C&G Ledger_allocation'!AV:AV,'[1]C&G Ledger_allocation'!$H:$H,'salary allocation-v2'!$D22,'[1]C&G Ledger_allocation'!$A:$A,'salary allocation-v2'!$N22) -> #VALUE! | V22: =SUMIFS('[1]C&G Ledger_allocation'!AW:AW,'[1]C&G Ledger_allocation'!$H:$H,'salary allocation-v2'!$D22,'[1]C&G Ledger_allocation'!$A:$A,'salary allocation-v2'!$N22) -> #VALUE! | W22: =SUMIFS('[1]C&G Ledger_allocation'!AX:AX,'[1]C&G Ledger_allocation'!$H:$H,'salary allocation-v2'!$D22,'[1]C&G Ledger_allocation'!$A:$A,'salary allocation-v2'!$N22) -> #VALUE! | X22: =SUMIFS('[1]C&G Ledger_allocation'!AY:AY,'[1]C&G Ledger_allocation'!$H:$H,'salary allocation-v2'!$D22,'[1]C&G Ledger_allocation'!$A:$A,'salary allocation-v2'!$N22) -> #VALUE! | Y22: =SUMIFS('[1]C&G Ledger_allocation'!AZ:AZ,'[1]C&G Ledger_allocation'!$H:$H,'salary allocation-v2'!$D22,'[1]C&G Ledger_allocation'!$A:$A,'salary allocation-v2'!$N22) -> #VALUE! | Z22: =SUMIFS('[1]C&G Ledger_allocation'!BA:BA,'[1]C&G Ledger_allocation'!$H:$H,'salary allocation-v2'!$D22,'[1]C&G Ledger_allocation'!$A:$A,'salary allocation-v2'!$N22) -> #VALUE! | AA22: =SUMIFS('[1]C&G Ledger_allocation'!BB:BB,'[1]C&G Ledger_allocation'!$H:$H,'salary allocation-v2'!$D22,'[1]C&G Ledger_allocation'!$A:$A,'salary allocation-v2'!$N22) -> #VALUE! | AB22: =SUMIFS('[1]C&G Ledger_allocation'!BC:BC,'[1]C&G Ledger_allocation'!$H:$H,'salary allocation-v2'!$D22,'[1]C&G Ledger_allocation'!$A:$A,'salary allocation-v2'!$N22) -> #VALUE! | AC22: =P22 -> #VALUE! | AD22: =$AC22*E22 -> #VALUE! | AE22: =$AC22*F22 -> #VALUE! | AF22: =$AC22*G22 -> #VALUE! | AG22: =$AC22*H22 -> #VALUE! | AH22: =$AC22*I22 -> #VALUE! | AI22: =$AC22*J22 -> #VALUE! | AJ22: =SUM(AD22:AI22) -> #VALUE! | AK22: =AC22-AJ22 -> #VALUE!
B24: Vietnam Tax Company | P24: =SUM(P22) -> #VALUE! | Q24: =SUM(Q6:Q7,Q14:Q19) -> #VALUE! | R24: =SUM(R11,R12,R20,R21) -> #VALUE! | W24: =SUM(W8,W9,W10,W11,W13) -> #VALUE! | AC24: =SUM(O24:AB24) -> #VALUE! | AD24: =SUM(AD6:AD23) -> #VALUE! | AE24: =SUM(AE6:AE23) -> #VALUE! | AF24: =SUM(AF6:AF23) -> #VALUE! | AG24: =SUM(AG6:AG23) -> #VALUE! | AH24: =SUM(AH6:AH23) -> #VALUE! | AI24: =SUM(AI6:AI23) -> #VALUE! | AJ24: =SUM(AJ6:AJ23) -> #VALUE!
